LICENSE.md
README.md
pyproject.toml
src/ewoksbm29/__init__.py
src/ewoksbm29.egg-info/PKG-INFO
src/ewoksbm29.egg-info/SOURCES.txt
src/ewoksbm29.egg-info/dependency_links.txt
src/ewoksbm29.egg-info/entry_points.txt
src/ewoksbm29.egg-info/requires.txt
src/ewoksbm29.egg-info/top_level.txt
src/ewoksbm29/apps/__init__.py
src/ewoksbm29/blissdata/__init__.py
src/ewoksbm29/blissdata/blissdatav1.py
src/ewoksbm29/blissdata/blissdatav2.py
src/ewoksbm29/io/__init__.py
src/ewoksbm29/io/read_offline.py
src/ewoksbm29/io/read_online.py
src/ewoksbm29/models/__init__.py
src/ewoksbm29/models/dahu.py
src/ewoksbm29/models/ispyb.py
src/ewoksbm29/tasks/__init__.py
src/ewoksbm29/tasks/hplc_summary.py
src/ewoksbm29/tasks/integrate.py
src/ewoksbm29/tasks/read.py
src/ewoksbm29/tasks/results.py
src/ewoksbm29/tasks/subtract.py
src/ewoksbm29/tasks/base/__init__.py
src/ewoksbm29/tasks/base/dahu.py
src/ewoksbm29/tasks/base/dahu_ispyb.py
src/ewoksbm29/tests/__init__.py
src/ewoksbm29/tests/conftest.py
src/ewoksbm29/tests/test_accumulation.py
src/ewoksbm29/tests/test_models.py
src/ewoksbm29/tests/test_workflows.py
src/ewoksbm29/tests/mock/hdf5_data.py
src/ewoksbm29/tests/mock/mock_tango.py
src/ewoksbm29/workflows/__init__.py
src/ewoksbm29/workflows/hplc_summary.json
src/ewoksbm29/workflows/integrate.json
src/ewoksbm29/workflows/run.py
src/ewoksbm29/workflows/subtract.json