Metadata-Version: 2.4
Name: ewoksbm29
Version: 1.0.0
Summary: Data processing workflows for BM29
Author-email: ESRF <dau-pydev@esrf.fr>
License: # MIT License
Project-URL: Homepage, https://gitlab.esrf.fr/workflow/ewoksapps/ewoksbm29/
Project-URL: Documentation, https://ewoksbm29.readthedocs.io/
Project-URL: Repository, https://gitlab.esrf.fr/workflow/ewoksapps/ewoksbm29/
Project-URL: Issues, https://gitlab.esrf.fr/workflow/ewoksapps/ewoksbm29/issues
Project-URL: Changelog, https://gitlab.esrf.fr/workflow/ewoksapps/ewoksbm29/-/blob/main/CHANGELOG.md
Keywords: ewoks
Classifier: Intended Audience :: Science/Research
Classifier: License :: OSI Approved :: MIT License
Classifier: Programming Language :: Python :: 3
Requires-Python: >=3.8
License-File: LICENSE.md
Requires-Dist: ewokscore
Requires-Dist: packaging
Provides-Extra: saxs
Requires-Dist: pydantic; extra == "saxs"
Requires-Dist: ewoksppf; extra == "saxs"
Requires-Dist: ewoksjob; extra == "saxs"
Requires-Dist: silx; extra == "saxs"
Provides-Extra: online
Requires-Dist: ewoksbm29[saxs]; extra == "online"
Requires-Dist: blissdata>=1; extra == "online"
Requires-Dist: redis-om!=1.0.0b0; python_version < "3.9" and extra == "online"
Requires-Dist: pytango; extra == "online"
Provides-Extra: test
Requires-Dist: ewoksbm29[online]; extra == "test"
Requires-Dist: pytest>=7; extra == "test"
Provides-Extra: dev
Requires-Dist: ewoksbm29[test]; extra == "dev"
Requires-Dist: black>=25; extra == "dev"
Requires-Dist: flake8>=4; extra == "dev"
Provides-Extra: doc
Requires-Dist: ewoksbm29[test]; extra == "doc"
Requires-Dist: sphinx>=4.5; extra == "doc"
Requires-Dist: sphinx-autodoc-typehints>=1.16; extra == "doc"
Requires-Dist: pydata-sphinx-theme; extra == "doc"
Requires-Dist: ewokssphinx; extra == "doc"
Dynamic: license-file
